shape_constraints/__init__.py
shape_constraints/constraints.py
shape_constraints-0.0.1.dist-info/WHEEL
shape_constraints-0.0.1.dist-info/METADATA
shape_constraints-0.0.1.dist-info/RECORD
